screen_lens_wrapper.py
screen_lens/__init__.py
screen_lens/bin/screen_lens.sh
screen_lens-0.1.4.dist-info/LICENSE.md
screen_lens-0.1.4.dist-info/METADATA
screen_lens-0.1.4.dist-info/WHEEL
screen_lens-0.1.4.dist-info/entry_points.txt
screen_lens-0.1.4.dist-info/top_level.txt
screen_lens-0.1.4.dist-info/RECORD
