Metadata-Version: 2.1
Name: screen-lens
Version: 0.1.4
Summary: Perform Google Lens search by taking a simple screenshot from anywhere in your system.
Home-page: https://github.com/sanchittanwar7/screen-lens
Author: Sanchit Tanwar
Author-email: connectwithme@sanchittanwar7.in
License: UNKNOWN
Platform: UNKNOWN
Classifier: Programming Language :: Python
Classifier: Programming Language :: Unix Shell
Requires-Python: >=3.7
License-File: LICENSE.md
Requires-Dist: requests
Requires-Dist: urllib3
